rabbit_manager/__init__.py
rabbit_manager/manager.py
rabbit_manager-0.2.0.dist-info/licenses/LICENSE
rabbit_manager-0.2.0.dist-info/METADATA
rabbit_manager-0.2.0.dist-info/WHEEL
rabbit_manager-0.2.0.dist-info/top_level.txt
rabbit_manager-0.2.0.dist-info/RECORD
