Metadata-Version: 2.4
Name: rabbit-manager
Version: 0.2.0
Summary: Lightweight RabbitMQ manager built on top of pika
Author-email: Viktor Viskov <carrergt@gmail.com>, Viktor Viskov <mail@viktorviskov.com>
License: MIT
Project-URL: Homepage, https://github.com/ViktorViskov/rabbit-manager
Project-URL: Source, https://github.com/ViktorViskov/rabbit-manager
Keywords: rabbitmq,pika,queue,message-queue,messaging
Classifier: Programming Language :: Python :: 3
Classifier: Programming Language :: Python :: 3 :: Only
Classifier: License :: OSI Approved :: MIT License
Classifier: Operating System :: OS Independent
Classifier: Topic :: Software Development :: Libraries
Requires-Python: >=3.10
License-File: LICENSE
Requires-Dist: pika>=1.3.2
Provides-Extra: dev
Requires-Dist: pytest>=7.0.0; extra == "dev"
Requires-Dist: pytest-cov>=4.0.0; extra == "dev"
Dynamic: license-file
